neptun/__init__.py
neptun/__main__.py
neptun/bot/__init__.py
neptun/bot/chat.py
neptun/bot/static/style.css
neptun/bot/tui.py
neptun/cli.py
neptun/cmd/__init__.py
neptun/cmd/assistant.py
neptun/cmd/auth.py
neptun/cmd/collection.py
neptun/cmd/config.py
neptun/cmd/github.py
neptun/cmd/health.py
neptun/cmd/info.py
neptun/cmd/open.py
neptun/cmd/project.py
neptun/cmd/template.py
neptun/config/config.ini
neptun/config/default.json
neptun/config/extension.json
neptun/config/info.toml
neptun/config/temp.ini
neptun/model/__init__.py
neptun/model/http_requests.py
neptun/model/http_responses.py
neptun/model/responses.py
neptun/test.py
neptun/utils/.DS_Store
neptun/utils/__init__.py
neptun/utils/dicts.py
neptun/utils/exceptions.py
neptun/utils/helpers.py
neptun/utils/managers.py
neptun/utils/services.py
neptun-0.1.12.dist-info/LICENSE
neptun-0.1.12.dist-info/METADATA
neptun-0.1.12.dist-info/WHEEL
neptun-0.1.12.dist-info/entry_points.txt
neptun-0.1.12.dist-info/RECORD
