Metadata-Version: 2.1
Name: neptun
Version: 0.1.12
Summary: Neptun is a Python-based CLI for interacting with Neptun AI via the Neptun API interface, designed to answer questions on DevOps, Docker, Docker Compose, and more.
License: MIT
Author: stevan06v
Requires-Python: >=3.12,<4.0
Classifier: License :: OSI Approved :: MIT License
Classifier: Programming Language :: Python :: 3
Classifier: Programming Language :: Python :: 3.12
Classifier: Programming Language :: Python :: 3.13
Requires-Dist: colorama (>=0.4.6,<0.5.0)
Requires-Dist: configparser (>=7.0.0,<8.0.0)
Requires-Dist: datetime (>=5.5,<6.0)
Requires-Dist: httpx (>=0.27.0,<0.28.0)
Requires-Dist: httpx-cache (>=0.13.0,<0.14.0)
Requires-Dist: mdformat (>=0.7.22,<0.8.0)
Requires-Dist: pydantic (>=2.10.4,<3.0.0)
Requires-Dist: pyfiglet (>=1.0.2,<2.0.0)
Requires-Dist: pytest (>=8.2.2,<9.0.0)
Requires-Dist: questionary (>=2.0.1,<3.0.0)
Requires-Dist: textual (>=0.76.0,<0.77.0)
Requires-Dist: toml (>=0.10.2,<0.11.0)
Requires-Dist: typer (>=0.15.1,<0.16.0)
